windows_tools.file_utils-0.3.0-py3.8-nspkg.pth
windows_tools/file_utils/__init__.py
windows_tools.file_utils-0.3.0.dist-info/LICENSE
windows_tools.file_utils-0.3.0.dist-info/METADATA
windows_tools.file_utils-0.3.0.dist-info/WHEEL
windows_tools.file_utils-0.3.0.dist-info/namespace_packages.txt
windows_tools.file_utils-0.3.0.dist-info/top_level.txt
windows_tools.file_utils-0.3.0.dist-info/RECORD
